MANIFEST.in
README.rst
setup.py
cloudshell_sandboxapi_wrapper/SandboxAPI.py
cloudshell_sandboxapi_wrapper/__init__.py
cloudshell_sandboxapi_wrapper.egg-info/PKG-INFO
cloudshell_sandboxapi_wrapper.egg-info/SOURCES.txt
cloudshell_sandboxapi_wrapper.egg-info/dependency_links.txt
cloudshell_sandboxapi_wrapper.egg-info/requires.txt
cloudshell_sandboxapi_wrapper.egg-info/top_level.txt