Metadata-Version: 1.1
Name: cloudshell-sandboxapi-wrapper
Version: 1.0.0
Summary: Python wrapper for CloudShell Sandbox API
Home-page: http://www.quali.com
Author: sadanand.s
Author-email: sadanand.s@quali.com
License: Apache 2.0
Platform: UNKNOWN
Classifier: License :: OSI Approved :: Apache Software License
Classifier: Natural Language :: English
Classifier: Programming Language :: Python :: 2.7
Classifier: Programming Language :: Python :: 3.7
Classifier: Programming Language :: Python :: 3.8
